utrunner/__init__.py
utrunner/__main__.py
utrunner/jsontestrunner.py
utrunner/utrunner.py
utrunner/wrappers.py
utrunner-0.3.0.dist-info/LICENSE
utrunner-0.3.0.dist-info/METADATA
utrunner-0.3.0.dist-info/WHEEL
utrunner-0.3.0.dist-info/top_level.txt
utrunner-0.3.0.dist-info/RECORD
